[{
    "avatar": "https://blog-1257031229.cos.ap-shanghai.myqcloud.com/matery/friends/cjdm.jpg",
    "name": "咖啡店的码农",
    "introduction": "Refresh it",
    "url": "https://marscheng.cn/",
    "title": "刷新一下"
  }, {
    "avatar": "https://blog-1257031229.cos.ap-shanghai.myqcloud.com/matery/friends/gaogong.jpg",
    "name": "客栈少年高工",
    "introduction": "clear cache",
    "url": "https://innlad.com/",
    "title": "清除缓存"
  }, {
    "avatar": "https://blog-1257031229.cos.ap-shanghai.myqcloud.com/matery/friends/avatar.png",
    "name": "换成吴彦祖",
    "introduction": "Reset computer.",
    "url": "http://zhangchengkang.top",
    "title": "重启电脑"
  }]